anydeck/__init__.py
anydeck/anydeck.py
AnyDeck-0.1.8.dist-info/LICENSE
AnyDeck-0.1.8.dist-info/METADATA
AnyDeck-0.1.8.dist-info/WHEEL
AnyDeck-0.1.8.dist-info/top_level.txt
AnyDeck-0.1.8.dist-info/RECORD
