Metadata-Version: 2.1
Name: AnyDeck
Version: 0.1.8
Summary: Generates a deck of virtually any type of cards from which drawing, adding, removing, and shuffling is handled by the module.
Home-page: https://github.com/tomamore/anydeck
Author: Thomas Amore Jr.
License: UNKNOWN
Project-URL: Bug Tracker, https://github.com/tomamore/anydeck/issues
Platform: UNKNOWN
Classifier: Programming Language :: Python :: 3
Classifier: Programming Language :: Python :: 3.6
Classifier: Programming Language :: Python :: 3.7
Classifier: Programming Language :: Python :: 3.8
Classifier: Programming Language :: Python :: 3.9
Classifier: Programming Language :: Python :: 3.10
Classifier: License :: OSI Approved :: MIT License
Classifier: Operating System :: OS Independent
Classifier: Development Status :: 4 - Beta
Classifier: Intended Audience :: Developers
Classifier: Intended Audience :: Education
Classifier: Topic :: Games/Entertainment
Classifier: Topic :: Games/Entertainment :: Board Games
Classifier: Topic :: Games/Entertainment :: Simulation
Requires-Python: >=3.6
License-File: LICENSE
